dag_converter/__init__.py
dag_converter/cleanup.py
dag_converter/cli.py
dag_converter/console_config.py
dag_converter/conversion_manager.py
dag_converter/dag_comparator.py
dag_converter/dagbag.py
dag_converter/py.typed
dag_converter/schema_parser.py
dag_converter/static_validator.py
dag_converter/taskflow_parser.py
dag_converter/validator_schema.yaml
dag_converter/yaml_format.py
dag_converter/yaml_validator.py
dag_converter/conversion/__init__.py
dag_converter/conversion/converter.py
dag_converter/conversion/default_args.py
dag_converter/conversion/dynamic_mapping.py
dag_converter/conversion/exceptions.py
dag_converter/conversion/schedule.py
dag_converter/conversion/tasks.py
dag_converter/conversion/operators/__init__.py
dag_converter/conversion/operators/python_decorator.py
python_to_yaml_dag_converter_mwaa_serverless-0.1.1.dist-info/METADATA
python_to_yaml_dag_converter_mwaa_serverless-0.1.1.dist-info/WHEEL
python_to_yaml_dag_converter_mwaa_serverless-0.1.1.dist-info/entry_points.txt
python_to_yaml_dag_converter_mwaa_serverless-0.1.1.dist-info/licenses/LICENSE
python_to_yaml_dag_converter_mwaa_serverless-0.1.1.dist-info/licenses/NOTICE
python_to_yaml_dag_converter_mwaa_serverless-0.1.1.dist-info/RECORD
