Metadata-Version: 2.4
Name: python-to-yaml-dag-converter-mwaa-serverless
Version: 0.1.1
Summary: CLI tool that converts Python airflow Dags to YAML Dags for use with dagfactory
Project-URL: Source, https://github.com/awslabs/python-to-yaml-dag-converter-mwaa-serverless
Project-URL: Repository, https://github.com/awslabs/python-to-yaml-dag-converter-mwaa-serverless.git
Project-URL: Issues, https://github.com/awslabs/python-to-yaml-dag-converter-mwaa-serverless/issues
Project-URL: Changelog, https://github.com/awslabs/python-to-yaml-dag-converter-mwaa-serverless/blob/main/CHANGELOG.md
Project-URL: Documentation, https://github.com/awslabs/python-to-yaml-dag-converter-mwaa-serverless/blob/main/README.md
License-File: LICENSE
License-File: NOTICE
Classifier: Development Status :: 4 - Beta
Classifier: Framework :: Apache Airflow
Classifier: Intended Audience :: Developers
Classifier: License :: OSI Approved :: Apache Software License
Classifier: Programming Language :: Python :: 3.11
Classifier: Programming Language :: Python :: 3.12
Requires-Python: >=3.11
Requires-Dist: apache-airflow-providers-amazon==9.10.0
Requires-Dist: apache-airflow-providers-cncf-kubernetes==10.6.1
Requires-Dist: apache-airflow==3.0.6
Requires-Dist: boto3>=1.37.3
Requires-Dist: dag-factory==1.0.0
Requires-Dist: fastapi[standard]==0.121.2
Requires-Dist: rich<15.0.0,>=13.7.1
